drf_secure_token/__init__.py
drf_secure_token/abstract_models.py
drf_secure_token/admin.py
drf_secure_token/apps.py
drf_secure_token/authentication.py
drf_secure_token/checkers.py
drf_secure_token/middleware.py
drf_secure_token/models.py
drf_secure_token/settings.py
drf_secure_token/tasks.py
drf_secure_token/migrations/0001_initial.py
drf_secure_token/migrations/0002_token_expire_in.py
drf_secure_token/migrations/0003_auto_20151223_0921.py
drf_secure_token/migrations/0004_auto_20160422_0837.py
drf_secure_token/migrations/0005_auto_20170227_1038.py
drf_secure_token/migrations/0006_auto_20170227_1945.py
drf_secure_token/migrations/0007_auto_20190920_1044.py
drf_secure_token/migrations/__init__.py
drf_secure_token-1.2.0.dist-info/METADATA
drf_secure_token-1.2.0.dist-info/WHEEL
drf_secure_token-1.2.0.dist-info/top_level.txt
drf_secure_token-1.2.0.dist-info/RECORD
