Metadata-Version: 2.1
Name: drf-secure-token
Version: 1.2.0
Summary: Add secure token to django-rest-framework
Home-page: 
Author: Tima Akulich
Author-email: tima.akulich@gmail.com
License: BSD License
Classifier: Environment :: Web Environment
Classifier: Framework :: Django
Classifier: Intended Audience :: Developers
Classifier: License :: OSI Approved :: BSD License
Classifier: Operating System :: OS Independent
Classifier: Programming Language :: Python
Classifier: Programming Language :: Python :: 3
Classifier: Topic :: Internet :: WWW/HTTP
Classifier: Topic :: Internet :: WWW/HTTP :: Dynamic Content
Requires-Dist: djangorestframework
